{
    "variables": [
        {
            "name": "tDrvFoc.tIabcFbck.f16Arg1",
            "address": 536871778,
            "var_type": "INT16",
            "byte_size": 2,
            "post_process": "SCALE",
            "scale_factor": 0.00211,
            "offset_value": 0.0,
            "enabled": true,
            "display_name": "",
            "description": "",
            "writable": false,
            "is_enum": false,
            "enum_values": {}
        },
        {
            "name": "tDrvFoc.tPospeControl.f16wRotE1",
            "address": 536871878,
            "var_type": "INT16",
            "byte_size": 2,
            "post_process": "SCALE",
            "scale_factor": 0.122,
            "offset_value": 0.0,
            "enabled": true,
            "display_name": "",
            "description": "",
            "writable": false,
            "is_enum": false,
            "enum_values": {}
        },
        {
            "name": "g_f16IqCompVal",
            "address": 536871232,
            "var_type": "INT16",
            "byte_size": 2,
            "post_process": "NONE",
            "scale_factor": 1.0,
            "offset_value": 0.0,
            "enabled": true,
            "display_name": "",
            "description": "",
            "writable": false,
            "is_enum": false,
            "enum_values": {}
        },
        {
            "name": "tDrvFoc.tPospeControl.f16ThetaRotEl",
            "address": 536871876,
            "var_type": "INT16",
            "byte_size": 2,
            "post_process": "NONE",
            "scale_factor": 1.0,
            "offset_value": 0.0,
            "enabled": true,
            "display_name": "",
            "description": "",
            "writable": false,
            "is_enum": false,
            "enum_values": {}
        },
        {
            "name": "tDrvFoc.tIDQFbck.f16Arg2",
            "address": 536871738,
            "var_type": "INT16",
            "byte_size": 2,
            "post_process": "NONE",
            "scale_factor": 1.0,
            "offset_value": 0.0,
            "enabled": true,
            "display_name": "",
            "description": "",
            "writable": false,
            "is_enum": false,
            "enum_values": {}
        },
        {
            "name": "f16ThetaMech",
            "address": 536871252,
            "var_type": "INT16",
            "byte_size": 2,
            "post_process": "NONE",
            "scale_factor": 1.0,
            "offset_value": 0.0,
            "enabled": true,
            "display_name": "",
            "description": "",
            "writable": false,
            "is_enum": false,
            "enum_values": {}
        }
    ]
}