{
    "variables": [
        {
            "name": "tDrvFoc.tIabcFbck.f16Arg1",
            "address": 536871766,
            "var_type": "INT16",
            "byte_size": 2,
            "post_process": "NONE",
            "scale_factor": 1.0,
            "offset_value": 0.0,
            "enabled": true,
            "display_name": "",
            "description": "",
            "writable": false,
            "is_enum": false,
            "enum_values": {}
        },
        {
            "name": "tDrvFoc.tPospeControl.f16wRotE1",
            "address": 536871866,
            "var_type": "INT16",
            "byte_size": 2,
            "post_process": "SCALE",
            "scale_factor": 0.122,
            "offset_value": 0.0,
            "enabled": true,
            "display_name": "",
            "description": "",
            "writable": false,
            "is_enum": false,
            "enum_values": {}
        },
        {
            "name": "tDrvFoc.tPospeControl.f16wRotElReqRamp",
            "address": 536871872,
            "var_type": "INT16",
            "byte_size": 2,
            "post_process": "SCALE",
            "scale_factor": 0.122,
            "offset_value": 0.0,
            "enabled": true,
            "display_name": "",
            "description": "",
            "writable": false,
            "is_enum": false,
            "enum_values": {}
        },
        {
            "name": "tDrvFoc.f16Idcbus",
            "address": 536871764,
            "var_type": "INT16",
            "byte_size": 2,
            "post_process": "NONE",
            "scale_factor": 1.0,
            "offset_value": 0.0,
            "enabled": true,
            "display_name": "",
            "description": "",
            "writable": false,
            "is_enum": false,
            "enum_values": {}
        },
        {
            "name": "headwind_machine_speed_flt",
            "address": 536871448,
            "var_type": "INT16",
            "byte_size": 2,
            "post_process": "NONE",
            "scale_factor": 1.0,
            "offset_value": 0.0,
            "enabled": false,
            "display_name": "",
            "description": "",
            "writable": false,
            "is_enum": false,
            "enum_values": {}
        },
        {
            "name": "tWmObsvr_PLL.tWmDir",
            "address": 536871608,
            "var_type": "UINT8",
            "byte_size": 1,
            "post_process": "NONE",
            "scale_factor": 1.0,
            "offset_value": 0.0,
            "enabled": false,
            "display_name": "",
            "description": "",
            "writable": false,
            "is_enum": false,
            "enum_values": {}
        },
        {
            "name": "headwind_bemf_theta",
            "address": 536871444,
            "var_type": "INT16",
            "byte_size": 2,
            "post_process": "NONE",
            "scale_factor": 1.0,
            "offset_value": 0.0,
            "enabled": false,
            "display_name": "",
            "description": "",
            "writable": false,
            "is_enum": false,
            "enum_values": {}
        },
        {
            "name": "tWmObsvr_PLL.tUabcBemf.f16Arg1",
            "address": 536871564,
            "var_type": "INT16",
            "byte_size": 2,
            "post_process": "NONE",
            "scale_factor": 1.0,
            "offset_value": 0.0,
            "enabled": false,
            "display_name": "",
            "description": "",
            "writable": false,
            "is_enum": false,
            "enum_values": {}
        },
        {
            "name": "tWmObsvr_PLL.tUabc.f16Arg1",
            "address": 536871570,
            "var_type": "INT16",
            "byte_size": 2,
            "post_process": "NONE",
            "scale_factor": 1.0,
            "offset_value": 0.0,
            "enabled": false,
            "display_name": "",
            "description": "",
            "writable": false,
            "is_enum": false,
            "enum_values": {}
        },
        {
            "name": "tWmObsvr_PLL.tUabc.f16Arg2",
            "address": 536871572,
            "var_type": "INT16",
            "byte_size": 2,
            "post_process": "NONE",
            "scale_factor": 1.0,
            "offset_value": 0.0,
            "enabled": false,
            "display_name": "",
            "description": "",
            "writable": false,
            "is_enum": false,
            "enum_values": {}
        },
        {
            "name": "tWmObsvr_PLL.tUabc.f16Arg3",
            "address": 536871574,
            "var_type": "INT16",
            "byte_size": 2,
            "post_process": "NONE",
            "scale_factor": 1.0,
            "offset_value": 0.0,
            "enabled": false,
            "display_name": "",
            "description": "",
            "writable": false,
            "is_enum": false,
            "enum_values": {}
        },
        {
            "name": "tWmObsvr_PLL.tBemfUAlBe.f16Arg1",
            "address": 536871610,
            "var_type": "INT16",
            "byte_size": 2,
            "post_process": "NONE",
            "scale_factor": 1.0,
            "offset_value": 0.0,
            "enabled": false,
            "display_name": "",
            "description": "",
            "writable": false,
            "is_enum": false,
            "enum_values": {}
        },
        {
            "name": "tWmObsvr_PLL.tBemfUAlBe.f16Arg2",
            "address": 536871612,
            "var_type": "INT16",
            "byte_size": 2,
            "post_process": "NONE",
            "scale_factor": 1.0,
            "offset_value": 0.0,
            "enabled": false,
            "display_name": "",
            "description": "",
            "writable": false,
            "is_enum": false,
            "enum_values": {}
        },
        {
            "name": "headwind_pll_error_input",
            "address": 536871450,
            "var_type": "INT16",
            "byte_size": 2,
            "post_process": "NONE",
            "scale_factor": 1.0,
            "offset_value": 0.0,
            "enabled": false,
            "display_name": "",
            "description": "",
            "writable": false,
            "is_enum": false,
            "enum_values": {}
        }
    ]
}